lightecho_stellar_oracle.py
lightecho_oracle_sdk-0.1.0.dist-info/METADATA
lightecho_oracle_sdk-0.1.0.dist-info/WHEEL
lightecho_oracle_sdk-0.1.0.dist-info/RECORD
