Metadata-Version: 2.1
Name: lightecho-oracle-sdk
Version: 0.1.0
Summary: Python SDK for the Lightecho Stellar Oracle
Home-page: https://github.com/bp-ventures/lightecho-stellar-oracle/tree/trunk/oracle-sdk/python
Author: BP Ventures
Requires-Python: >=3.11,<4.0
Classifier: Programming Language :: Python :: 3
Classifier: Programming Language :: Python :: 3.11
Requires-Dist: stellar-sdk (==9.0.0b0)
